django_csv_export-0.0.3.dist-info/DESCRIPTION.rst
django_csv_export-0.0.3.dist-info/METADATA
django_csv_export-0.0.3.dist-info/RECORD
django_csv_export-0.0.3.dist-info/WHEEL
django_csv_export-0.0.3.dist-info/metadata.json
django_csv_export-0.0.3.dist-info/top_level.txt
export_csv/__init__.py
export_csv/apps.py
export_csv/exceptions.py
export_csv/views.py
export_csv/migrations/__init__.py
