Metadata-Version: 2.0
Name: django-csv-export
Version: 0.0.3
Summary: django-export-csv is a reusable Django application which provides generic View class for creating and rendering CSV.
Home-page: https://github.com/narenchoudhary/django-export-csv/tree/master
Author: Narendra Choudhary
Author-email: narendralegha.mail@gmail.com
License: BSD
Keywords: django library development
Platform: UNKNOWN
Classifier: Development Status :: 4 - Beta
Classifier: Environment :: Web Environment
Classifier: Framework :: Django
Classifier: Framework :: Django :: 1.7
Classifier: Framework :: Django :: 1.8
Classifier: Framework :: Django :: 1.9
Classifier: Framework :: Django :: 1.10
Classifier: Intended Audience :: Developers
Classifier: License :: OSI Approved :: BSD License
Classifier: Natural Language :: English
Classifier: Operating System :: OS Independent
Classifier: Programming Language :: Python
Classifier: Programming Language :: Python :: 2
Classifier: Programming Language :: Python :: 2.7
Classifier: Programming Language :: Python :: 3.3
Classifier: Programming Language :: Python :: 3.4
Classifier: Programming Language :: Python :: 3.5
Classifier: Topic :: Internet :: WWW/HTTP
Classifier: Topic :: Software Development :: Libraries :: Python Modules
Requires-Dist: Django (>=1.7)
